.gitignore
.pylintrc
CMakeLists.txt
CONTRIBUTING.md
LICENSE
README.md
build.sh
clean_all.sh
pyproject.toml
setup.py
test.sh
.github/workflows/hanabi-publish.yml
.github/workflows/pylint.yml
.vscode/c_cpp_properties.json
.vscode/launch.json
bad/__init__.py
bad/action_network.py
bad/action_provider.py
bad/bad_agent.py
bad/bad_agent_acting_result.py
bad/bad_setting.py
bad/baseline.py
bad/bayesian_action.py
bad/bayesian_action_result.py
bad/collect_batch_results.py
bad/collect_episode_data.py
bad/collect_game_result.py
bad/constants.py
bad/game_buffer.py
bad/policy.py
bad/reward_shape.py
bad/reward_shape_converter.py
bad/reward_shape_result.py
bad/reward_to_go_calculation.py
bad/rewards_to_go_calculation_result.py
bad/rewards_to_go_episode_calculation_result.py
bad/rewardshape_setting.py
bad/run_episode_result.py
bad/run_eposiode.py
bad/self_play.py
bad/set_extra_observation.py
bad/train_batch_result.py
bad/train_batches.py
bad/train_epoch.py
bad/train_epoch_result.py
bad/belief/__init__.py
bad/belief/build_hanabi_env.py
bad/belief/ftpubvec.py
bad/belief/hint_matrix_global.py
bad/belief/hint_matrix_hand_card.py
bad/belief/hint_matrix_player.py
bad/belief/likelihood_global.py
bad/belief/likelihood_hand_card.py
bad/belief/likelihood_player.py
bad/belief/public_belief_global.py
bad/belief/public_belief_hand_card.py
bad/belief/public_belief_player.py
bad/encoding/__init__.py
bad/encoding/card.py
bad/encoding/card_probabilitiy.py
bad/encoding/colortointconverter.py
bad/encoding/fireworkrank.py
bad/encoding/hands.py
bad/encoding/legal_actions.py
bad/encoding/observation.py
bad/encoding/observationconverter.py
bad/encoding/privatefeatures.py
bad/encoding/public_belief_global_enc.py
bad/encoding/public_belief_hand_card_enc.py
bad/encoding/public_belief_player_enc.py
bad/encoding/publicfeatures.py
bad/encoding/ranktointconverter.py
bad/encoding/rem_cards_to_int_converter.py
examples/CMakeLists.txt
examples/README.md
examples/game_example.cc
examples/game_example.py
ws2223_group7_hanabi_learning_environment_bad.egg-info/PKG-INFO
ws2223_group7_hanabi_learning_environment_bad.egg-info/SOURCES.txt
ws2223_group7_hanabi_learning_environment_bad.egg-info/dependency_links.txt
ws2223_group7_hanabi_learning_environment_bad.egg-info/entry_points.txt
ws2223_group7_hanabi_learning_environment_bad.egg-info/requires.txt
ws2223_group7_hanabi_learning_environment_bad.egg-info/top_level.txt