Metadata-Version: 2.1
Name: ws2223-group7-hanabi-learning-environment-bad
Version: 0.0.13
Summary: ws2223-group7 Learning environment for the game of hanabi bad agent.
Home-page: UNKNOWN
Author: ws2223-group7/hanabi-learning-environment_bad
License: UNKNOWN
Platform: UNKNOWN
Classifier: Programming Language :: Python :: 3
Classifier: Operating System :: POSIX :: Linux
Requires-Python: >=3.6
License-File: LICENSE
